{"info": {"institution": "Department of Computer Science\n47 Lab Campus Drive", "occupation": "professor", "summary": "Andrea Pohoreckyj Danyluk works as a professor in Department of Computer Science\n47 Lab Campus Drive, and his\\her h-index is 12, g-index is 26. His\\Her interests are :\n Machine Learning; Event-driven Program...; Williams College; Computer Science; Eighteenth Internati...;", "org": "unknown", "numberOfFollowers": 0, "interests": ["Machine Learning", "Event-driven Program...", "Williams College", "Computer Science", "Eighteenth Internati..."]}, "name": "Andrea Pohoreckyj Danyluk", "am_id": "53f475b4dabfaec09f27bb43"}