{"info": {"institution": "Department of Computer Science, University of Manchester", "occupation": "Professor", "summary": "Carole A. Goble works as a Professor in Department of Computer Science, University of Manchester, and his\\her h-index is 79, g-index is 150. His\\Her interests are :\n Web Service; Semantic Web; Ontology; Bioinformatics; Scientific Workflows;", "org": "unknown", "numberOfFollowers": 0, "interests": ["Web Service", "Semantic Web", "Ontology", "Bioinformatics", "Scientific Workflows"]}, "name": "Carole A. Goble", "am_id": "53f479c8dabfae8a6845bfe1"}