{"info": {"institution": "Research Assistant in Institute of Information Science, Academia Sinica", "occupation": "unknown", "summary": "Chien Chin Chen works as a unknown in Research Assistant in Institute of Information Science, Academia Sinica, and his\\her h-index is 13, g-index is 30. His\\Her interests are :\n Text Mining; Classification; Hidden Markov Models; Internet; Symmetric Matrices;", "org": "unknown", "numberOfFollowers": 0, "interests": ["Text Mining", "Classification", "Hidden Markov Models", "Internet", "Symmetric Matrices"]}, "name": "Chien Chin Chen", "am_id": "53f42b48dabfaeb22f3e6895"}