{"info": {"institution": "Stanford Univ., Stanford, CA", "occupation": "unknown", "summary": "David E. Rumelhart works as a unknown in Stanford Univ., Stanford, CA, and his\\her h-index is 38, g-index is 0. His\\Her interests are :\n Neural Network; Information Processi...; Parallel Distributed...; Cognitive Processes; Interactive Activati...;", "org": "unknown", "numberOfFollowers": 0, "interests": ["Neural Network", "Information Processi...", "Parallel Distributed...", "Cognitive Processes", "Interactive Activati..."]}, "name": "David E. Rumelhart", "am_id": "53f8098adabfae938c6f6b9b"}