{"info": {"institution": "Operations and Information Management The Wharton School of the University of Pennsylvania", "occupation": "Professor", "summary": "Eric K. Clemons works as a Professor in Operations and Information Management The Wharton School of the University of Pennsylvania, and his\\her h-index is 36, g-index is 84. His\\Her interests are :\n Information System; Information Technolo...; Competitive Strategy; Profitability; Special Section;", "org": "unknown", "numberOfFollowers": 0, "interests": ["Information System", "Information Technolo...", "Competitive Strategy", "Profitability", "Special Section"]}, "name": "Eric K. Clemons", "am_id": "54868f2adabfae8a11fb3320"}