{"info": {"institution": "David R. Cheriton School of Computer Science at the University of Waterloo", "occupation": "Associate Professor", "summary": "Grant E. Weddell works as a Associate Professor in David R. Cheriton School of Computer Science at the University of Waterloo, and his\\her h-index is 18, g-index is 30. His\\Her interests are :\n Description Logic; Functional Dependenc...; Functional Constrain...; Query Language; Uniqueness Constrain...;", "org": "unknown", "numberOfFollowers": 0, "interests": ["Description Logic", "Functional Dependenc...", "Functional Constrain...", "Query Language", "Uniqueness Constrain..."]}, "name": "Grant E. Weddell", "am_id": "54854dbadabfae8a11fb2830"}