{"info": {"institution": "Faculty of Computer Science\r\nUniversity of New Brunswick\r\nSemantic Web Laboratory\r\n", "occupation": "Adjunct Professor\r\nLeader", "summary": "Harold Boley works as a Adjunct Professor\r\nLeader in Faculty of Computer Science\r\nUniversity of New Brunswick\r\nSemantic Web Laboratory\r\n, and his\\her h-index is 28, g-index is 51. His\\Her interests are :\n Semantic Web; Knowledge Representa...; Knowledge Base; Rule Responder; Description Logic;", "org": "unknown", "numberOfFollowers": 0, "interests": ["Semantic Web", "Knowledge Representa...", "Knowledge Base", "Rule Responder", "Description Logic"]}, "name": "Harold Boley", "am_id": "53f4375adabfaeee229b382d"}