{"info": {"institution": "Department of Computer Science", "occupation": "professor", "summary": "Jyrki Kivinen works as a professor in Department of Computer Science, and his\\her h-index is 18, g-index is 40. His\\Her interests are :\n Bregman Divergence; Gradient Descent; Input Variable; Machine Learning; Polynomial Time;", "org": "unknown", "numberOfFollowers": 0, "interests": ["Bregman Divergence", "Gradient Descent", "Input Variable", "Machine Learning", "Polynomial Time"]}, "name": "Jyrki Kivinen", "am_id": "53f49f29dabfaec18b77b568"}