{"info": {"institution": "Institute of Computer Science\nFoundation for Research and Technology - Hellas \n", "occupation": "Research Assistant\n", "summary": "Kyriakos Kritikos works as a Research Assistant\n in Institute of Computer Science\nFoundation for Research and Technology - Hellas \n, and his\\her h-index is 16, g-index is 34. His\\Her interests are :\n Web Service; Ontology; QOS; Quality Of Service; Service Discovery;", "org": "unknown", "numberOfFollowers": 0, "interests": ["Web Service", "Ontology", "QOS", "Quality Of Service", "Service Discovery"]}, "name": "Kyriakos Kritikos", "am_id": "53f45b11dabfaee0d9c0579f"}