{"info": {"institution": "Katholieke Universiteit Leuven", "occupation": "Professor", "summary": "Luc De Raedt works as a Professor in Katholieke Universiteit Leuven, and his\\her h-index is 71, g-index is 140. His\\Her interests are :\n Data Mining; Inductive Logic Prog...; Machine Learning; Statistical Relation...; Relational Learning;", "org": "unknown", "numberOfFollowers": 0, "interests": ["Data Mining", "Inductive Logic Prog...", "Machine Learning", "Statistical Relation...", "Relational Learning"]}, "name": "Luc De Raedt", "am_id": "53f48bbadabfaea7cd1ccb54"}