{"info": {"institution": "CWI, Dutch research center for mathematics and computer Science", "occupation": "unknown", "summary": "Marcel Holsheimer works as a unknown in CWI, Dutch research center for mathematics and computer Science, and his\\her h-index is 7, g-index is 12. His\\Her interests are :\n Data Mining; Complex Object; Data Structure; Data Surveyor; Database Interface;", "org": "unknown", "numberOfFollowers": 0, "interests": ["Data Mining", "Complex Object", "Data Structure", "Data Surveyor", "Database Interface"]}, "name": "Marcel Holsheimer", "am_id": "53f44b05dabfaee0d9bc67de"}