{"info": {"institution": "CSAIL, MIT", "occupation": "Chief Scientist", "summary": "Michael L. Brodie works as a Chief Scientist in CSAIL, MIT, and his\\her h-index is 31, g-index is 75. His\\Her interests are :\n Artificial Intellige...; Semantic Web; Data Model; Information System; Distributed Computin...;", "org": "unknown", "numberOfFollowers": 0, "interests": ["Artificial Intellige...", "Semantic Web", "Data Model", "Information System", "Distributed Computin..."]}, "name": "Michael L. Brodie", "am_id": "53f48458dabfaee43ed5c724"}