{"info": {"institution": "Department of Computer Science,Stony Brook University", "occupation": "Professor", "summary": "Michael Kifer works as a Professor in Department of Computer Science,Stony Brook University, and his\\her h-index is 46, g-index is 117. His\\Her interests are :\n Transaction Logic; Semantic Web; Logic Programming; Model Theory; Knowledge Representa...;", "org": "unknown", "numberOfFollowers": 0, "interests": ["Transaction Logic", "Semantic Web", "Logic Programming", "Model Theory", "Knowledge Representa..."]}, "name": "Michael Kifer", "am_id": "53f4347bdabfaeb22f45f789"}