{"info": {"institution": "1 F-319B, Bellcore, 445 South Street, Morristown, NJ", "occupation": "unknown", "summary": "Nachimuthu Karunanithi works as a unknown in 1 F-319B, Bellcore, 445 South Street, Morristown, NJ, and his\\her h-index is 9, g-index is 15. His\\Her interests are :\n Neural Network; Genetic Algorithm; Case Study; Neural Nets; Predictions;", "org": "unknown", "numberOfFollowers": 0, "interests": ["Neural Network", "Genetic Algorithm", "Case Study", "Neural Nets", "Predictions"]}, "name": "Nachimuthu Karunanithi", "am_id": "53f4756edabfaeee22a8ba05"}