{"info": {"institution": "IIIT, India", "occupation": "unknown", "summary": "Soujanya Vadapalli works as a unknown in IIIT, India, and his\\her h-index is 4, g-index is 12. His\\Her interests are :\n Data Visualisation; High Dimensional Dat...; Heidi Visualization; Materialized Views; Data Warehousing;", "org": "unknown", "numberOfFollowers": 0, "interests": ["Data Visualisation", "High Dimensional Dat...", "Heidi Visualization", "Materialized Views", "Data Warehousing"]}, "name": "Soujanya Vadapalli", "am_id": "53f43724dabfaee0d9b6b748"}