{"info": {"institution": "Knowledge Media Institute, The Open University, Milton Keynes, UK", "occupation": "Research Fellow", "summary": "Stefania Galizia works as a Research Fellow in Knowledge Media Institute, The Open University, Milton Keynes, UK, and his\\her h-index is 8, g-index is 22. His\\Her interests are :\n Semantic Web Service; Semantic Web; Web Service; Service Provider; Trusted Semantic Web...;", "org": "unknown", "numberOfFollowers": 0, "interests": ["Semantic Web Service", "Semantic Web", "Web Service", "Service Provider", "Trusted Semantic Web..."]}, "name": "Stefania Galizia", "am_id": "53f374b4dabfae4b349ccde9"}