{"info": {"institution": "Computer Science \r\n University of Brescia", "occupation": "full professor of Computer Science", "summary": "Valeria De Antonellis works as a full professor of Computer Science in Computer Science \r\n University of Brescia, and his\\her h-index is 22, g-index is 40. His\\Her interests are :\n Service Discovery; Information System; Web Apis; Web Service; Conceptual Schema;", "org": "unknown", "numberOfFollowers": 0, "interests": ["Service Discovery", "Information System", "Web Apis", "Web Service", "Conceptual Schema"]}, "name": "Valeria De Antonellis", "am_id": "53f55caadabfae4f09f8045b"}