{"info": {"institution": "Institute of Astronautics & Aeronautics,University of Electronic Science and Technology of China,Chengdu ,China", "occupation": "unknown", "summary": "Xi Bai works as a unknown in Institute of Astronautics & Aeronautics,University of Electronic Science and Technology of China,Chengdu ,China, and his\\her h-index is 22, g-index is 44. His\\Her interests are :\n", "org": "unknown", "numberOfFollowers": 0, "interests": []}, "name": "Xi Bai", "am_id": "53f7c5cddabfae938c6da2e2"}