{"info": {"institution": "Vehicle Research Laboratory, Nissan Research Center, Nissan Motor Co., Ltd., Natsushima-cho 1, Yokosuka-shi, Kanagawa 237-8523, Japan", "occupation": "unknown", "summary": "Yuji Takada works as a unknown in Vehicle Research Laboratory, Nissan Research Center, Nissan Motor Co., Ltd., Natsushima-cho 1, Yokosuka-shi, Kanagawa 237-8523, Japan, and his\\her h-index is 9, g-index is 17. His\\Her interests are :\n Control Set; Grammatical Inferenc...; Linear Language; Context Free Languag...; Equal Matrix;", "org": "unknown", "numberOfFollowers": 0, "interests": ["Control Set", "Grammatical Inferenc...", "Linear Language", "Context Free Languag...", "Equal Matrix"]}, "name": "Yuji Takada", "am_id": "53f439ecdabfaee2a1d06f57"}