{"info": {"institution": "University of Queensland", "occupation": "unknown", "summary": "Zoran Milosevic works as a unknown in University of Queensland, and his\\her h-index is 21, g-index is 39. His\\Her interests are :\n Business Process; Business Contract; Electronic Commerce; Croatian; Hrvatski;", "org": "unknown", "numberOfFollowers": 0, "interests": ["Business Process", "Business Contract", "Electronic Commerce", "Croatian", "Hrvatski"]}, "name": "Zoran Milosevic", "am_id": "54844a95dabfaed7b5fa18e1"}