{"authorList": [{"aff": {}, "avatar": "https://static.aminer.org/picture/499/1225208263674.jpeg", "bind": false, "id": "53f48e1ddabfaeaa2ef8045b", "indices": {"activity": 37.1415, "citations": 1223, "diversity": 3.7475, "gindex": 31, "hindex": 20, "newStar": 4.1366, "pubs": 84, "risingStar": 4.1366, "sociability": 4.3694}, "name": "Bruno Cr\u00e9milleux", "name_zh": "", "num_followed": 0, "num_upvoted": 0, "num_viewed": 2582, "profile": {"affiliation": "Universit\u00e9 de Caen", "position": " Professor"}, "score": 9721.943, "sourcetype": "", "tags": ["Data Mining", "Condensed Representation", "Local Pattern", "Association Rule", "Large Set", "Search Space", "Missing Values", "Constraint Solver", "Data Mining Technique", "Anti-Monotone Constraint", "Satisfiability", "Emerging Pattern", "Constraint Programming", "Text Mining", "Data Mining Method", "Natural Language Processing", "Whole Set", "Large Data", "Rules", "Extensions"], "tags_score": [20, 6, 6, 6, 6, 5, 5, 3, 3, 3, 3, 3, 3, 3, 3, 2, 2, 2, 2, 2], "tags_translated_zh": ["\u6570\u636e\u6316\u6398", "\u7cbe\u7b80\u96c6", "\u5c40\u90e8\u6a21\u5f0f", "\u5173\u8054\u89c4\u5219", "\u5927\u96c6", "\u641c\u7d22\u7a7a\u95f4", "\u7f3a\u5931\u503c", "\u7ea6\u675f\u6c42\u89e3", "\u6570\u636e\u6316\u6398\u6280\u672f", "\u53ef\u6ee1\u8db3\u6027", "\u663e\u9732\u6a21\u5f0f", "\u7ea6\u675f\u89c4\u5212", "\u6587\u672c\u6316\u6398", "\u6570\u636e\u6316\u6398\u65b9\u6cd5", "\u81ea\u7136\u8bed\u8a00\u5904\u7406", "\u6574\u673a", "\u6d77\u91cf\u6570\u636e", "\u89c4\u5f8b", "\u6570\u636e\u6a21\u578b\u6269\u5c55"]}, {"bind": false, "id": "53f435f7dabfaedf4357c124", "indices": {"activity": 0.0131, "citations": 260, "diversity": 1.3573, "gindex": 16, "hindex": 8, "newStar": 0, "pubs": 33, "risingStar": 0, "sociability": 4.3307}, "name": "Bruno Cremilleux", "name_zh": "", "num_followed": 0, "num_upvoted": 0, "num_viewed": 34, "profile": {"affiliation": "Universit\u00e9 de Caen", "org": "Department of Medical Informatics, Medical Faculty, University of Grenoble, B.P. 217, Grenoble, France 38043", "position": " Professor"}, "score": 4304.347, "sourcetype": "", "tags": ["Data Mining", "Satisfiability", "Meningitis", "Suitable Property", "Contrasts", "Mining Plausible Patterns", "Expression Data", "Gene Group", "Medical Consulting System", "Expert System", "Search Space", "Pattern Discovery Process", "Biological Situation", "Cp Paradigm", "Declarative Pattern Discovery", "Consecutive Case", "Additional Knowledge", "K Recursive", "Large Collection", "Data Class"], "tags_score": [5, 2, 1, 1, 1, 1, 1, 1, 1, 1, 1, 1, 1, 1, 1, 1, 1, 1, 1, 1], "tags_translated_zh": ["\u6570\u636e\u6316\u6398", "\u53ef\u6ee1\u8db3\u6027", "\u8111\u819c\u708e", "\u5bf9\u6bd4", "\u8868\u8fbe\u6570\u636e", "\u57fa\u56e0\u7ec4", "\u4e13\u5bb6\u7cfb\u7edf", "\u641c\u7d22\u7a7a\u95f4", "\u6570\u636e\u7c7b"]}, {"aff": {}, "bind": false, "id": "562d30eb45cedb3398d825d2", "indices": {"activity": 0, "citations": 4, "diversity": 0, "gindex": 1, "hindex": 1, "newStar": 0, "pubs": 1, "risingStar": 0, "sociability": 1.0986}, "name": "Bruno Cr\u00e9milleux", "num_followed": 0, "num_upvoted": 0, "score": 956.551, "sourcetype": "", "tags": [], "tags_translated_zh": []}, {"bind": false, "id": "561d16ad45ce1e596472e5cd", "indices": {"activity": 0, "citations": 22, "diversity": 0, "gindex": 1, "hindex": 1, "newStar": 0, "pubs": 1, "risingStar": 0, "sociability": 2.3025}, "name": "Cr\u00e9milleux Bruno", "num_followed": 0, "num_upvoted": 0, "num_viewed": 2, "profile": {"affiliation": "\u2020Normandie Universit\u00e9, Caen, France.", "org": "\u2020Normandie Universit\u00e9, Caen, France."}, "score": 677.84686, "sourcetype": "", "tags": [], "tags_translated_zh": []}, {"bind": false, "id": "561e380045ce1e59648db719", "indices": {"activity": 1.0253, "citations": 3, "diversity": 0, "gindex": 1, "hindex": 1, "newStar": 1.0253, "pubs": 1, "risingStar": 1.0253, "sociability": 2.0794}, "name": "Cr\u00e9milleux Bruno", "num_followed": 0, "num_upvoted": 0, "num_viewed": 3, "profile": {"affiliation": "Universit\u00e9 de Caen, GREYC, UMR6072, Caen, F-14032 France.", "org": "Universit\u00e9 de Caen, GREYC, UMR6072, Caen, F-14032 France."}, "score": 677.84686, "sourcetype": "", "tags": ["Natural Language Processing", "Sequential Pattern Mining", "Information Extraction", "Data Mining", "Gene Interactions"], "tags_score": [1, 1, 1, 1, 1], "tags_translated_zh": ["\u81ea\u7136\u8bed\u8a00\u5904\u7406", "\u5e8f\u5217\u6a21\u5f0f\u6316\u6398", "\u4fe1\u606f\u63d0\u53d6", "\u6570\u636e\u6316\u6398", "\u57fa\u56e0\u76f8\u4e92\u4f5c\u7528"]}, {"bind": false, "id": "562cabab45cedb3398c8ec67", "indices": {"activity": 0.1619, "citations": 0, "diversity": 0, "gindex": 0, "hindex": 0, "newStar": 0.1922, "pubs": 1, "risingStar": 0.1922, "sociability": 1.6094}, "name": "Bruno Cr\u00e9milleux", "num_followed": 0, "num_upvoted": 0, "num_viewed": 2, "score": 478.2859, "sourcetype": "", "tags": [], "tags_translated_zh": []}]}