{"authorList": [{"aff": {}, "avatar": "https://static.aminer.org/upload/avatar/610/1792/1702/53f479c3dabfae8a6845beab.jpeg", "bind": false, "id": "53f479c3dabfae8a6845beab", "indices": {"activity": 18.609, "citations": 4393, "diversity": 3.0551, "gindex": 63, "hindex": 34, "newStar": 6.6635, "pubs": 225, "risingStar": 6.6635, "sociability": 6.2822}, "name": "Jean-Marc Petit", "name_zh": "", "num_followed": 0, "num_upvoted": 0, "num_viewed": 48, "profile": {"affiliation": "Departement IF, INSA Lyon,LIRIS \u2013 UMR 5205 CNRS ,Universit\u00e9 de Lyon", "position": "Professeur"}, "score": 17547.367, "sourcetype": "", "tags": ["Data Mining", "Solar System", "Functional Dependency", "Relational Database", "Relational Databases", "Satisfiability", "Asteroids", "Data Streams", "Pervasive Environment", "Numerical Integration", "Pervasive Application", "Management System", "Services", "Implications", "Rules", "Power Law", "Databases", "Origin", "Thermodynamics", "Kuiper Belt"], "tags_score": [21, 13, 11, 11, 9, 7, 6, 6, 5, 5, 5, 5, 5, 4, 4, 4, 4, 3, 3, 3], "tags_translated_zh": ["\u6570\u636e\u6316\u6398", "\u592a\u9633\u7cfb", "\u51fd\u6570\u4f9d\u8d56", "\u5173\u7cfb\u6570\u636e\u5e93", "\u5173\u7cfb\u6570\u636e\u5e93", "\u53ef\u6ee1\u8db3\u6027", "\u5c0f\u884c\u661f", "\u6570\u636e\u6d41", "\u666e\u9002\u73af\u5883", "\u6570\u503c\u79ef\u5206", "\u7ba1\u7406\u7cfb\u7edf", "\u670d\u52a1", "\u9690\u55bb", "\u89c4\u5f8b", "\u5e42\u5f8b\u8c31", "\u6570\u636e\u5e93", "\u8d77\u6e90", "\u70ed\u529b\u5b66", "kuiper\u5e26"]}, {"bind": false, "id": "562c3cc145cedb3398bc8de6", "indices": {"activity": 0.0982, "citations": 1, "diversity": 0, "gindex": 1, "hindex": 1, "newStar": 0.0982, "pubs": 1, "risingStar": 0.0982, "sociability": 0.6931}, "name": "Jean-Marc Petit", "num_followed": 0, "num_upvoted": 0, "num_viewed": 3, "score": 994.95544, "sourcetype": "", "tags": [], "tags_translated_zh": []}, {"bind": false, "id": "562cdc1845cedb3398ce7dbd", "indices": {"activity": 0.4383, "citations": 7, "diversity": 0, "gindex": 1, "hindex": 1, "newStar": 0.5203, "pubs": 1, "risingStar": 0.5203, "sociability": 1.3862}, "name": "Jean-Marc Petit", "num_followed": 0, "num_upvoted": 0, "num_viewed": 5, "score": 988.57434, "sourcetype": "", "tags": [], "tags_translated_zh": []}, {"bind": false, "id": "562caba945cedb3398c8ec2e", "indices": {"activity": 0.0972, "citations": 0, "diversity": 0, "gindex": 0, "hindex": 0, "newStar": 0.1154, "pubs": 1, "risingStar": 0.1154, "sociability": 0}, "name": "Jean-Marc Petit", "num_followed": 0, "num_upvoted": 0, "score": 494.28717, "sourcetype": "", "tags": [], "tags_translated_zh": []}, {"bind": false, "id": "53f47b86dabfaee43ed4614e", "indices": {"activity": 0, "citations": 1, "diversity": 0, "gindex": 1, "hindex": 1, "newStar": 0, "pubs": 10, "risingStar": 0, "sociability": 3.0445}, "name": "Jean-Marc C. Petit", "name_zh": "", "num_followed": 0, "num_upvoted": 0, "num_viewed": 2, "profile": {"affiliation": "LAOB", "org": "LAOB"}, "score": 34.002716, "sourcetype": "", "tags": [], "tags_translated_zh": []}, {"bind": false, "id": "5610174e45ce1e59620356bb", "indices": {"activity": 0, "citations": 0, "diversity": 0, "gindex": 0, "hindex": 0, "newStar": 0, "pubs": 1, "risingStar": 0, "sociability": 2.639}, "name": "Petit Jean-Marc", "num_followed": 0, "num_upvoted": 0, "score": 16.948029, "sourcetype": "", "tags": [], "tags_translated_zh": []}]}