{"authorList": [{"aff": {}, "avatar": "https://static.aminer.org/upload/avatar/1997/964/1915/53f43c9edabfaee0d9b99cf5.jpeg", "bind": false, "id": "53f43c9edabfaee0d9b99cf5", "indices": {"activity": 37.3747, "citations": 18911, "diversity": 3.6261, "gindex": 136, "hindex": 52, "newStar": 2.6046, "pubs": 266, "risingStar": 2.6046, "sociability": 5.9348}, "name": "Wynne Hsu", "name_zh": "", "num_followed": 1, "num_upvoted": 0, "num_viewed": 3539, "profile": {"affiliation": "School of Computing, National University of Singapore", "position": "Professor"}, "score": 24536.514, "sourcetype": "", "tags": ["Data Mining", "Indexation", "Association Rule Mining", "Association Rule", "Data Structure", "Experiment Result", "Feature Extraction", "Data Cleaning", "Classification", "Xml", "Xml Document", "Domain Knowledge", "Personalization", "Image Retrieval", "Image Segmentation", "Search Space", "Machine Learning", "Path Expressions", "Satisfiability", "Image Classification"], "tags_score": [41, 12, 10, 10, 8, 8, 7, 6, 6, 6, 6, 6, 6, 5, 5, 5, 5, 5, 5, 5], "tags_translated_zh": ["\u6570\u636e\u6316\u6398", "\u6307\u6570\u5316", "\u5173\u8054\u89c4\u5219\u6316\u6398", "\u5173\u8054\u89c4\u5219", "\u6570\u636e\u7ed3\u6784", "\u5b9e\u9a8c\u7ed3\u679c", "\u7279\u5f81\u63d0\u53d6", "\u6570\u636e\u6e05\u7406", "\u5206\u7c7b", "\u53ef\u6269\u5c55\u6807\u8bb0\u8bed\u8a00", "xml\u6587\u6863", "\u9886\u57df\u77e5\u8bc6", "\u4e2a\u6027\u5316", "\u56fe\u50cf\u68c0\u7d22", "\u56fe\u50cf\u5206\u5272", "\u641c\u7d22\u7a7a\u95f4", "\u673a\u5668\u5b66\u4e60", "\u5e76\u884c\u7b97\u6cd5", "\u53ef\u6ee1\u8db3\u6027", "\u56fe\u50cf\u5206\u7c7b"]}, {"bind": false, "id": "562ce17b45cedb3398cf1574", "indices": {"activity": 7.7365, "citations": 16, "diversity": 0, "gindex": 1, "hindex": 1, "newStar": 9.1828, "pubs": 1, "risingStar": 9.1828, "sociability": 1.0986}, "name": "Wynne Hsu", "num_followed": 0, "num_upvoted": 0, "num_viewed": 4, "score": 956.57355, "sourcetype": "", "tags": ["Source Reliability", "Entity Profiling", "Record Linkage", "Data Mining", "Truth Discovery"], "tags_score": [1, 1, 1, 1, 1], "tags_translated_zh": ["\u8bb0\u5f55\u94fe\u63a5", "\u6570\u636e\u6316\u6398"]}, {"bind": false, "id": "56077e7545ce1e595f12c1c3", "indices": {"activity": 0, "citations": 30, "diversity": 0, "gindex": 1, "hindex": 1, "newStar": 0, "pubs": 1, "risingStar": 0, "sociability": 2.0794}, "name": "Hsu Wynne", "num_followed": 0, "num_upvoted": 0, "num_viewed": 5, "score": 692.95447, "sourcetype": "", "tags": [], "tags_translated_zh": []}, {"bind": false, "id": "5625c73745ce1e5965104f3b", "indices": {"activity": 0, "citations": 62, "diversity": 0, "gindex": 1, "hindex": 1, "newStar": 0, "pubs": 1, "risingStar": 0, "sociability": 2.0794}, "name": "Hsu Wynne", "num_followed": 0, "num_upvoted": 0, "num_viewed": 3, "score": 677.8484, "sourcetype": "", "tags": [], "tags_translated_zh": []}, {"bind": false, "id": "5628375745ce1e5965d7da30", "indices": {"activity": 0, "citations": 86, "diversity": 0, "gindex": 1, "hindex": 1, "newStar": 0, "pubs": 1, "risingStar": 0, "sociability": 2.3978}, "name": "Hsu Wynne", "num_followed": 0, "num_upvoted": 0, "num_viewed": 3, "score": 677.8484, "sourcetype": "", "tags": [], "tags_translated_zh": []}, {"bind": false, "id": "560843f345ce1e595f505b3f", "indices": {"activity": 0, "citations": 1, "diversity": 0, "gindex": 1, "hindex": 1, "newStar": 0, "pubs": 1, "risingStar": 0, "sociability": 2.3025}, "name": "Hsu Wynne", "num_followed": 0, "num_upvoted": 0, "num_viewed": 4, "score": 657.51495, "sourcetype": "", "tags": ["Correlation", "Reproducibility", "Stereoscopic"], "tags_score": [1, 1, 1], "tags_translated_zh": ["\u76f8\u5173", "\u91cd\u590d\u6027", "\u7acb\u4f53\u79cd\u690d"]}, {"bind": false, "id": "5625cd6445ce1e59651311e8", "indices": {"activity": 0, "citations": 0, "diversity": 0, "gindex": 0, "hindex": 0, "newStar": 0, "pubs": 1, "risingStar": 0, "sociability": 2.1972}, "name": "Hsu Wynne", "num_followed": 0, "num_upvoted": 0, "num_viewed": 1, "score": 346.47723, "sourcetype": "", "tags": [], "tags_translated_zh": []}, {"bind": false, "id": "562fae3e45ceb49c5d77b4fe", "indices": {"activity": 0, "citations": 0, "diversity": 0, "gindex": 0, "hindex": 0, "newStar": 0, "pubs": 1, "risingStar": 0, "sociability": 2.1972}, "name": "Hsu Wynne", "num_followed": 0, "num_upvoted": 0, "num_viewed": 3, "score": 346.4692, "sourcetype": "", "tags": [], "tags_translated_zh": []}, {"bind": false, "id": "56315fc745ceb49c5e0b8e68", "indices": {"activity": 0, "citations": 0, "diversity": 0, "gindex": 0, "hindex": 0, "newStar": 0, "pubs": 1, "risingStar": 0, "sociability": 2.4849}, "name": "Hsu Wynne", "num_followed": 0, "num_upvoted": 0, "num_viewed": 2, "score": 338.9242, "sourcetype": "", "tags": [], "tags_translated_zh": []}, {"bind": false, "id": "5625675b45ce1e5964e7fafb", "indices": {"activity": 0, "citations": 0, "diversity": 0, "gindex": 0, "hindex": 0, "newStar": 0, "pubs": 1, "risingStar": 0, "sociability": 2.1972}, "name": "Hsu Wynne", "num_followed": 0, "num_upvoted": 0, "num_viewed": 2, "score": 328.75748, "sourcetype": "", "tags": [], "tags_translated_zh": []}, {"bind": false, "id": "5613f2de45ce1e59632ad78e", "indices": {"activity": 0, "citations": 0, "diversity": 0, "gindex": 0, "hindex": 0, "newStar": 0, "pubs": 1, "risingStar": 0, "sociability": 2.4849}, "name": "Hsu Wynne", "num_followed": 0, "num_upvoted": 0, "score": 328.75748, "sourcetype": "", "tags": [], "tags_translated_zh": []}]}