{"authorList": [{"bind": false, "id": "53f799b9dabfae9060ad11ee", "indices": {"activity": 66.2708, "citations": 8297, "diversity": 4.163, "gindex": 78, "hindex": 48, "newStar": 35.284, "pubs": 500, "risingStar": 35.284, "sociability": 6.7557}, "name": "Zhao Yang Dong", "name_zh": "", "num_followed": 0, "num_upvoted": 0, "num_viewed": 948, "profile": {"affiliation": "Hong Kong Polytechnic University(Hong Kong Polytechnic University,The Hong Kong Polytechnic University),Hong Kong,China", "org": "Hong Kong Polytechnic University(Hong Kong Polytechnic University,The Hong Kong Polytechnic University),Hong Kong,China"}, "score": 21073.895, "sourcetype": "", "tags": ["Power System", "Power Quality", "Electric Power Systems", "Power Systems", "Power Distribution", "Smart Grid", "Virtual Power Plant", "Advanced Control", "Power Flow", "Fault Diagnosis", "Power Grids", "Process Planning", "Economic Dispatch", "Power Market", "Power Transmission", "Wind Turbine", "Transmission Lines", "Wind Generators", "Time Domain", "Dynamic Analysis"], "tags_score": [80.88942, 80.20733, 79.68875, 76.81363, 74.7873, 74.70558, 73.798645, 73.537315, 73.13056, 72.09225, 71.839165, 69.9947, 69.46839, 68.81317, 68.79768, 68.431625, 68.37719, 68.0418, 67.898026, 67.897514], "tags_translated_zh": ["\u98ce\u9669\u7ba1\u7406", "\u7a33\u5b9a\u6027", "\u7535\u529b\u5e02\u573a", "\u5206\u53c9", "\u7a33\u5b9a\u88d5\u5ea6", "\u7535\u529b\u7cfb\u7edf\u7a33\u5b9a", "\u9057\u4f20\u7b97\u6cd5", "\u5b89\u5168", "copula\u51fd\u6570", "\u98ce\u529b\u53d1\u7535", "\u6545\u969c\u6982\u7387", "\u7535\u529b\u7cfb\u7edf\u5b89\u5168", "\u667a\u80fd\u7535\u7f51", "\u51b0\u707e", "\u53c2\u6570\u8bc6\u522b"]}, {"bind": false, "id": "562f82f045cedb33996d2ba4", "indices": {"activity": 0, "citations": 9, "diversity": 0, "gindex": 1, "hindex": 1, "newStar": 0, "pubs": 1, "risingStar": 0, "sociability": 1.3862}, "name": "Zhao Yang Dong", "num_followed": 0, "num_upvoted": 0, "score": 956.55316, "sourcetype": "", "tags": [], "tags_translated_zh": []}, {"bind": false, "id": "562f6a0e45cedb339966b4f1", "indices": {"activity": 0, "citations": 19, "diversity": 0, "gindex": 1, "hindex": 1, "newStar": 0, "pubs": 1, "risingStar": 0, "sociability": 1.0986}, "name": "Zhao Yang Dong", "num_followed": 0, "num_upvoted": 0, "score": 925.924, "sourcetype": "", "tags": [], "tags_translated_zh": []}, {"bind": false, "id": "562d8aec45cedb3398e4ffc6", "indices": {"activity": 0, "citations": 209, "diversity": 0, "gindex": 1, "hindex": 1, "newStar": 0, "pubs": 1, "risingStar": 0, "sociability": 1.6094}, "name": "Zhao Yang Dong", "num_followed": 0, "num_upvoted": 0, "score": 905.71106, "sourcetype": "", "tags": [], "tags_translated_zh": []}, {"bind": false, "id": "562dc45345cedb3398ef1298", "indices": {"activity": 0, "citations": 13, "diversity": 0, "gindex": 1, "hindex": 1, "newStar": 0, "pubs": 1, "risingStar": 0, "sociability": 1.6094}, "name": "Zhao Yang Dong", "num_followed": 0, "num_upvoted": 0, "score": 905.71106, "sourcetype": "", "tags": [], "tags_translated_zh": []}, {"bind": false, "id": "562f4ade45cedb33995eee9e", "indices": {"activity": 0, "citations": 7, "diversity": 0, "gindex": 1, "hindex": 1, "newStar": 0, "pubs": 1, "risingStar": 0, "sociability": 0.6931}, "name": "Zhao-yang Dong", "num_followed": 0, "num_upvoted": 0, "profile": {"affiliation": "Dept. of Electr. Eng., Nat. Univ. of Singapore, Singapore|c|", "org": "Dept. of Electr. Eng., Nat. Univ. of Singapore, Singapore|c|"}, "score": 905.71106, "sourcetype": "", "tags": [], "tags_translated_zh": []}, {"bind": false, "id": "5631a44d45cedb3399eb2747", "indices": {"activity": 0, "citations": 23, "diversity": 0, "gindex": 1, "hindex": 1, "newStar": 0, "pubs": 1, "risingStar": 0, "sociability": 1.3862}, "name": "Zhao Yang Dong", "num_followed": 0, "num_upvoted": 0, "score": 890.60486, "sourcetype": "", "tags": [], "tags_translated_zh": []}, {"bind": false, "id": "5631ac7f45cedb3399ed1e58", "indices": {"activity": 0, "citations": 1, "diversity": 0, "gindex": 1, "hindex": 1, "newStar": 0, "pubs": 1, "risingStar": 0, "sociability": 0.6931}, "name": "Zhao Yang Dong", "num_followed": 0, "num_upvoted": 0, "score": 890.60486, "sourcetype": "", "tags": [], "tags_translated_zh": []}, {"bind": false, "id": "56312de145cedb3399ceb670", "indices": {"activity": 0, "citations": 11, "diversity": 0, "gindex": 1, "hindex": 1, "newStar": 0, "pubs": 1, "risingStar": 0, "sociability": 1.0986}, "name": "Zhao Yang Dong", "num_followed": 0, "num_upvoted": 0, "score": 890.60486, "sourcetype": "", "tags": [], "tags_translated_zh": []}, {"bind": false, "id": "563056cd45cedb33999fd203", "indices": {"activity": 0, "citations": 9, "diversity": 0, "gindex": 1, "hindex": 1, "newStar": 0, "pubs": 1, "risingStar": 0, "sociability": 1.0986}, "name": "Zhao Yang Dong", "num_followed": 0, "num_upvoted": 0, "score": 878.6251, "sourcetype": "", "tags": [], "tags_translated_zh": []}, {"bind": false, "id": "562f6a0a45cedb339966b3b0", "indices": {"activity": 0, "citations": 1, "diversity": 0, "gindex": 1, "hindex": 1, "newStar": 0, "pubs": 1, "risingStar": 0, "sociability": 0.6931}, "name": "Zhao Yang Dong", "num_followed": 0, "num_upvoted": 0, "score": 878.6251, "sourcetype": "", "tags": [], "tags_translated_zh": []}, {"bind": false, "id": "5630db5b45cedb3399bac270", "indices": {"activity": 0, "citations": 2, "diversity": 0, "gindex": 1, "hindex": 1, "newStar": 0, "pubs": 1, "risingStar": 0, "sociability": 1.3862}, "name": "Zhao Yang Dong", "num_followed": 0, "num_upvoted": 0, "score": 878.6251, "sourcetype": "", "tags": [], "tags_translated_zh": []}, {"bind": false, "id": "562fecae45cedb3399867b96", "indices": {"activity": 0, "citations": 1, "diversity": 0, "gindex": 1, "hindex": 1, "newStar": 0, "pubs": 1, "risingStar": 0, "sociability": 0.6931}, "name": "Zhao Yang Dong", "num_followed": 0, "num_upvoted": 0, "score": 878.62213, "sourcetype": "", "tags": [], "tags_translated_zh": []}, {"bind": false, "id": "562ffb8945cedb33998a6bcc", "indices": {"activity": 0, "citations": 4, "diversity": 0, "gindex": 1, "hindex": 1, "newStar": 0, "pubs": 1, "risingStar": 0, "sociability": 1.3862}, "name": "Zhao Yang Dong", "num_followed": 0, "num_upvoted": 0, "score": 878.62213, "sourcetype": "", "tags": [], "tags_translated_zh": []}, {"bind": false, "id": "5625889c45cedb33985cf8a6", "indices": {"activity": 0, "citations": 8, "diversity": 0, "gindex": 1, "hindex": 1, "newStar": 0, "pubs": 1, "risingStar": 0, "sociability": 1.6094}, "name": "Zhao Yang Dong", "num_followed": 0, "num_upvoted": 0, "score": 878.62213, "sourcetype": "", "tags": [], "tags_translated_zh": []}, {"bind": false, "id": "562dc4ea45cedb3398ef2f7a", "indices": {"activity": 0, "citations": 106, "diversity": 0, "gindex": 1, "hindex": 1, "newStar": 0, "pubs": 1, "risingStar": 0, "sociability": 1.6094}, "name": "Zhao Yang Dong", "num_followed": 0, "num_upvoted": 0, "score": 878.62213, "sourcetype": "", "tags": [], "tags_translated_zh": []}, {"bind": false, "id": "562f276945cedb339955d318", "indices": {"activity": 0, "citations": 26, "diversity": 0, "gindex": 1, "hindex": 1, "newStar": 0, "pubs": 1, "risingStar": 0, "sociability": 0.6931}, "name": "Zhao-yang Dong", "num_followed": 0, "num_upvoted": 0, "score": 860.15894, "sourcetype": "", "tags": [], "tags_translated_zh": []}, {"bind": false, "id": "5631bcd245cedb3399f09438", "indices": {"activity": 0, "citations": 7, "diversity": 0, "gindex": 1, "hindex": 1, "newStar": 0, "pubs": 1, "risingStar": 0, "sociability": 1.6094}, "name": "Zhao Yang Dong", "num_followed": 0, "num_upvoted": 0, "score": 860.15894, "sourcetype": "", "tags": [], "tags_translated_zh": []}, {"bind": false, "id": "562fb68d45cedb339979c6d6", "indices": {"activity": 0, "citations": 30, "diversity": 0, "gindex": 1, "hindex": 1, "newStar": 0, "pubs": 1, "risingStar": 0, "sociability": 1.0986}, "name": "Zhao Yang Dong", "num_followed": 0, "num_upvoted": 0, "score": 860.15894, "sourcetype": "", "tags": [], "tags_translated_zh": []}, {"bind": false, "id": "562ffb9145cedb33998a6d20", "indices": {"activity": 0, "citations": 6, "diversity": 0, "gindex": 1, "hindex": 1, "newStar": 0, "pubs": 1, "risingStar": 0, "sociability": 1.3862}, "name": "Zhao Yang Dong", "num_followed": 0, "num_upvoted": 0, "score": 860.15894, "sourcetype": "", "tags": [], "tags_translated_zh": []}, {"bind": false, "id": "56243b8645cedb33984e863e", "indices": {"activity": 0, "citations": 5, "diversity": 0, "gindex": 1, "hindex": 1, "newStar": 0, "pubs": 1, "risingStar": 0, "sociability": 1.3862}, "name": "Zhao Yang-Dong", "num_followed": 0, "num_upvoted": 0, "profile": {"affiliation": "First Branch(First Branch),Xi'an,China", "org": "First Branch(First Branch),Xi'an,China"}, "score": 860.15894, "sourcetype": "", "tags": [], "tags_translated_zh": []}, {"bind": false, "id": "562ede6745cedb3399419eeb", "indices": {"activity": 0, "citations": 0, "diversity": 0, "gindex": 0, "hindex": 0, "newStar": 0, "pubs": 1, "risingStar": 0, "sociability": 1.0986}, "name": "Zhao Yang Dong", "num_followed": 0, "num_upvoted": 0, "score": 478.27747, "sourcetype": "", "tags": [], "tags_translated_zh": []}, {"bind": false, "id": "56303f3a45cedb33999a1b53", "indices": {"activity": 0, "citations": 0, "diversity": 0, "gindex": 0, "hindex": 0, "newStar": 0, "pubs": 1, "risingStar": 0, "sociability": 1.6094}, "name": "Zhao Yang Dong", "num_followed": 0, "num_upvoted": 0, "score": 462.962, "sourcetype": "", "tags": [], "tags_translated_zh": []}, {"bind": false, "id": "562d8fbf45cedb3398e5cdf5", "indices": {"activity": 0, "citations": 0, "diversity": 0, "gindex": 0, "hindex": 0, "newStar": 0, "pubs": 1, "risingStar": 0, "sociability": 1.6094}, "name": "Zhao Yang Dong", "num_followed": 0, "num_upvoted": 0, "score": 445.30243, "sourcetype": "", "tags": [], "tags_translated_zh": []}, {"bind": false, "id": "562f1a1445cedb339952a248", "indices": {"activity": 0, "citations": 0, "diversity": 0, "gindex": 0, "hindex": 0, "newStar": 0, "pubs": 1, "risingStar": 0, "sociability": 1.0986}, "name": "Zhao-yang Dong", "num_followed": 0, "num_upvoted": 0, "score": 439.31256, "sourcetype": "", "tags": [], "tags_translated_zh": []}, {"bind": false, "id": "562f4e9a45cedb33995feda9", "indices": {"activity": 0, "citations": 0, "diversity": 0, "gindex": 0, "hindex": 0, "newStar": 0, "pubs": 1, "risingStar": 0, "sociability": 1.0986}, "name": "Zhao-yang Dong", "num_followed": 0, "num_upvoted": 0, "profile": {"affiliation": "Sch. of Comput. Sci. & Electr. Eng., Queensland Univ., St. Lucia, Qld., Australia|c|", "org": "Sch. of Comput. Sci. & Electr. Eng., Queensland Univ., St. Lucia, Qld., Australia|c|"}, "score": 439.31256, "sourcetype": "", "tags": [], "tags_translated_zh": []}, {"bind": false, "id": "56231ce045cedb3398436c8c", "indices": {"activity": 0, "citations": 0, "diversity": 0, "gindex": 0, "hindex": 0, "newStar": 0, "pubs": 1, "risingStar": 0, "sociability": 0.6931}, "name": "Zhao Yang-Dong", "num_followed": 0, "num_upvoted": 0, "profile": {"affiliation": "First Branch(First Branch),Xi'an,China", "org": "First Branch(First Branch),Xi'an,China"}, "score": 439.31107, "sourcetype": "", "tags": [], "tags_translated_zh": []}, {"bind": false, "id": "562eafc845cedb339933ff78", "indices": {"activity": 0, "citations": 0, "diversity": 0, "gindex": 0, "hindex": 0, "newStar": 0, "pubs": 1, "risingStar": 0, "sociability": 1.0986}, "name": "Zhao Yang Dong", "num_followed": 0, "num_upvoted": 0, "score": 430.07947, "sourcetype": "", "tags": [], "tags_translated_zh": []}, {"aff": {}, "bind": false, "id": "5631975e45cedb3399e86632", "indices": {"activity": 0, "citations": 9, "diversity": 0, "gindex": 3, "hindex": 2, "newStar": 0, "pubs": 3, "risingStar": 0, "sociability": 2.4849}, "name": "Dong, Zhao-yang", "num_followed": 0, "num_upvoted": 0, "profile": {"affiliation": "Department of Electrical Engineering, The Hong Kong Polytechnic University, Hong Kong|c|"}, "score": 36.96621, "sourcetype": "", "tags": ["Dynamic Simulation", "Power System Dynamics", "Load Modeling", "Load Model", "Electricity Price Forecasting", "Forecast Combination", "Sensitivity Analysis", "Eigenvalue Analysis", "Model Selection", "Rtds", "Model Validation", "Probabilistic Power System Small Signal Stability"], "tags_score": [1, 1, 1, 1, 1, 1, 1, 1, 1, 1, 1, 1], "tags_translated_zh": ["\u52a8\u6001\u6a21\u62df", "\u7535\u529b\u7cfb\u7edf\u52a8\u6001", "\u8d1f\u8377\u5efa\u6a21", "\u8d1f\u8377\u6a21\u578b", "\u7535\u4ef7\u9884\u6d4b", "\u7ec4\u5408\u9884\u6d4b", "\u7075\u654f\u5ea6\u5206\u6790", "\u7279\u5f81\u503c\u5206\u6790", "\u9009\u578b", "\u5b9e\u65f6\u6570\u5b57\u7cfb\u7edf", "\u6a21\u578b\u9a8c\u8bc1"]}, {"bind": false, "id": "543135b1dabfae8d7fade231", "indices": {"activity": 0, "citations": 31, "diversity": 0, "gindex": 5, "hindex": 2, "newStar": 0, "pubs": 5, "risingStar": 0, "sociability": 2.3025}, "name": "\u8463\u671d\u9633(Dong Zhao-Yang)", "name_zh": "\u8463\u671d\u9633", "num_followed": 0, "num_upvoted": 0, "profile": {"affiliation": "Cold and Arid Regions Environmental and Engineering Research Institute,CAS,LanZhou ,China; Graduate school of CAS,Beijing ,China", "org": "Cold and Arid Regions Environmental and Engineering Research Institute,CAS,LanZhou ,China; Graduate school of CAS,Beijing ,China"}, "score": 36.941223, "sourcetype": "", "tags": ["Desertification", "System Coupling", "Development", "Adjustment", "Land-Reclamation Enterprises", "Human Effect", "Reversion", "Animal Husbandry", "Dynamic Mechanism", "Benefit", "Hexi Region", "Research Advances", "Regional Effect", "Analog Computation", "Ecological Economy", "Heihe Basin", "Ecological Control Policy", "Sunan County"], "tags_score": [2, 2, 1, 1, 1, 1, 1, 1, 1, 1, 1, 1, 1, 1, 1, 1, 1, 1], "tags_translated_zh": ["\u6c99\u6f20\u5316", "\u7814\u5236", "\u5e73\u5dee", "\u53cd\u6f14", "\u755c\u7267\u4e1a", "\u52a8\u529b\u673a\u5236", "\u5229\u76ca", "\u7814\u7a76\u8fdb\u5c55", "\u6a21\u62df\u8ba1\u7b97", "\u751f\u6001\u7ecf\u6d4e"]}, {"bind": false, "id": "543135b1dabfae8d7fade238", "indices": {"activity": 0, "citations": 15, "diversity": 0, "gindex": 3, "hindex": 2, "newStar": 0, "pubs": 9, "risingStar": 0, "sociability": 2.3025}, "name": "\u8463\u671d\u9633(Dong Zhao-Yang)", "name_zh": "\u8463\u671d\u9633", "num_followed": 0, "num_upvoted": 0, "num_viewed": 1, "profile": {"affiliation": "Xi'an University of Architecture and Technology,Xi'an ,China", "org": "Xi'an University of Architecture and Technology,Xi'an ,China"}, "score": 36.917866, "sourcetype": "", "tags": ["Networked Manufacturing", "Optimizing Configuration", "Process Planning", "Modification Location", "Concurrent Integration", "Decision Support", "Multiple-Knapsack Problem", "Software Component Library", "Component Management Protocol", "Gear Hob", "Configuration Management Database", "Component Storage Model", "Shaving Cutter", "Service Oriented", "Uniform Service Architecture Platform", "Software Architecture", "Compromise-Based Parallel Multiple Objective Genetic Algorithm", "Faceted Scheme", "Hard Alloy", "Engaging Angle"], "tags_score": [2, 2, 1, 1, 1, 1, 1, 1, 1, 1, 1, 1, 1, 1, 1, 1, 1, 1, 1, 1], "tags_translated_zh": ["\u7f51\u7edc\u5316\u5236\u9020", "\u5de5\u827a\u8bbe\u8ba1", "\u51b3\u7b56\u652f\u6301", "\u914d\u7f6e\u7ba1\u7406\u6570\u636e\u5e93", "\u9762\u5411\u670d\u52a1", "\u8f6f\u4ef6\u4f53\u7cfb\u7ed3\u6784", "\u523b\u9762\u5206\u7c7b\u6cd5", "\u786c\u8d28\u5408\u91d1"]}, {"bind": false, "id": "53f46872dabfaeb22f545e38", "indices": {"activity": 0, "citations": 57, "diversity": 0, "gindex": 1, "hindex": 1, "newStar": 0, "pubs": 1, "risingStar": 0, "sociability": 2.1972}, "name": "Dong Yang Zhao", "name_zh": "", "num_followed": 0, "num_upvoted": 0, "profile": {"affiliation": "Tuberculosis Control Institute, Henan Provincial Center for Disease Control and Prevention, Xindong Districe 450016, Zhengzhou, China", "org": "Tuberculosis Control Institute, Henan Provincial Center for Disease Control and Prevention, Xindong Districe 450016, Zhengzhou, China"}, "score": 24.644138, "sourcetype": "", "tags": ["Parasitology", "Prevalence", "Young Adult", "Questionnaires", "Binary Logistic Regression", "Cross Sectional Study", "Risk Factors", "Medical Microbiology", "Cross Section", "Tropical Medicine", "Logistic Model", "Internal Medicine", "Infection Control", "Cross Sectional Studies"], "tags_score": [1, 1, 1, 1, 1, 1, 1, 1, 1, 1, 1, 1, 1, 1], "tags_translated_zh": ["\u5bc4\u751f\u866b\u5b66", "\u60a3\u75c5\u7387", "\u9752\u5e74\u4eba", "\u8c03\u67e5\u8868", "\u4e8c\u5143\u903b\u8f91\u56de\u5f52", "\u73b0\u51b5\u8c03\u67e5", "\u5371\u9669\u56e0\u7d20", "\u533b\u5b66\u5fae\u751f\u7269\u5b66", "\u622a\u9762", "\u70ed\u5e26\u533b\u5b66", "logistic\u6a21\u578b", "\u5185\u79d1", "\u611f\u67d3\u63a7\u5236", "\u6a2a\u65ad\u9762\u7814\u7a76"]}, {"bind": false, "id": "543135b1dabfae8d7fade23a", "indices": {"activity": 0, "citations": 1, "diversity": 0, "gindex": 1, "hindex": 1, "newStar": 0, "pubs": 4, "risingStar": 0, "sociability": 0}, "name": "\u8463\u671d\u9633(Dong Zhao-Yang)", "name_zh": "\u8463\u671d\u9633", "num_followed": 0, "num_upvoted": 0, "profile": {"org": ""}, "score": 24.644138, "sourcetype": "", "tags": [], "tags_translated_zh": []}, {"bind": false, "id": "56257d8145cedb33985c6d44", "indices": {"activity": 0, "citations": 11, "diversity": 0, "gindex": 1, "hindex": 1, "newStar": 0, "pubs": 1, "risingStar": 0, "sociability": 1.3862}, "name": "Yang Dong Zhao", "num_followed": 0, "num_upvoted": 0, "profile": {"affiliation": "Hong Kong Polytechnic University(Hong Kong Polytechnic University,The Hong Kong Polytechnic University),Hong Kong,China", "org": "Hong Kong Polytechnic University(Hong Kong Polytechnic University,The Hong Kong Polytechnic University),Hong Kong,China"}, "score": 24.640171, "sourcetype": "", "tags": [], "tags_translated_zh": []}, {"bind": false, "id": "543135b1dabfae8d7fade241", "indices": {"activity": 0, "citations": 1, "diversity": 0, "gindex": 1, "hindex": 1, "newStar": 0, "pubs": 1, "risingStar": 0, "sociability": 1.0986}, "name": "\u8463\u671d\u9633(Dong Zhao-Yang)", "name_zh": "\u8463\u671d\u9633", "num_followed": 0, "num_upvoted": 0, "num_viewed": 3, "profile": {"affiliation": "School of Information Technology and Electrical Engineering,University of Queensland,QLD 4067,Australia", "org": "School of Information Technology and Electrical Engineering,University of Queensland,QLD 4067,Australia"}, "score": 24.631826, "sourcetype": "", "tags": ["Prediction Interval", "Electricity Market Clearing Price", "Garch", "Bootstrap"], "tags_score": [1, 1, 1, 1], "tags_translated_zh": ["\u9884\u6d4b\u533a\u95f4", "garch\u6a21\u578b", "\u81ea\u4e3e"]}, {"bind": false, "id": "56071e7b45ce1e595ef06d67", "indices": {"activity": 0, "citations": 3, "diversity": 0, "gindex": 1, "hindex": 1, "newStar": 0, "pubs": 1, "risingStar": 0, "sociability": 1.3862}, "name": "Yang Dong-zhao", "num_followed": 0, "num_upvoted": 0, "score": 24.627481, "sourcetype": "", "tags": [], "tags_translated_zh": []}, {"bind": false, "id": "53f464fcdabfaee4dc8483ff", "indices": {"activity": 0, "citations": 13, "diversity": 0, "gindex": 1, "hindex": 1, "newStar": 0, "pubs": 1, "risingStar": 0, "sociability": 1.3862}, "name": "Dong Zhao-Yang", "name_zh": "", "num_followed": 0, "num_upvoted": 0, "profile": {"org": ""}, "score": 24.618034, "sourcetype": "", "tags": ["Restorative Control", "Partial Minimum Spanning Tree", "Power System Restoration", "System Reconfiguration", "Genetic Algorithm"], "tags_score": [1, 1, 1, 1, 1], "tags_translated_zh": ["\u7535\u529b\u7cfb\u7edf\u6062\u590d", "\u7cfb\u7edf\u91cd\u6784", "\u9057\u4f20\u7b97\u6cd5"]}, {"bind": false, "id": "5605f71445ce1e595e81731c", "indices": {"activity": 0, "citations": 0, "diversity": 0, "gindex": 0, "hindex": 0, "newStar": 0, "pubs": 1, "risingStar": 0, "sociability": 1.9459}, "name": "Dong Zhao-yang", "num_followed": 0, "num_upvoted": 0, "profile": {"affiliation": "Department of Burns and Plastic Surgery, Shanghai Corps Hospital, Chinese People's Armed Police Force, Shanghai, P. R. China 201103.", "org": "Department of Burns and Plastic Surgery, Shanghai Corps Hospital, Chinese People's Armed Police Force, Shanghai, P. R. China 201103."}, "score": 12.322069, "sourcetype": "", "tags": [], "tags_translated_zh": []}, {"bind": false, "id": "53f464fcdabfaee4dc8483fe", "indices": {"activity": 0, "citations": 0, "diversity": 0, "gindex": 0, "hindex": 0, "newStar": 0, "pubs": 1, "risingStar": 0, "sociability": 1.0986}, "name": "\u4e1c\u671d\u9633(Dong Zhao-Yang)", "name_zh": "\u4e1c\u671d\u9633", "num_followed": 0, "num_upvoted": 0, "profile": {"affiliation": "Power equipment state monitoring and control of Key Laboratory of the Ministry ofEducation(North China Electric Power University", "org": "Power equipment state monitoring and control of Key Laboratory of the Ministry ofEducation(North China Electric Power University"}, "score": 12.315913, "sourcetype": "", "tags": ["Thermodynamic Analysis", "Power Generation Systems of Solar Collectors", "Exergy Analysis"], "tags_score": [1, 1, 1], "tags_translated_zh": ["\u70ed\u529b\u5b66\u5206\u6790", "\u5206\u6790"]}, {"bind": false, "id": "53f464fcdabfaee4dc848405", "indices": {"activity": 0.0081, "citations": 0, "diversity": 0, "gindex": 0, "hindex": 0, "newStar": 0, "pubs": 1, "risingStar": 0, "sociability": 1.0986}, "name": "\u4e1c\u671d\u9633(Dong Zhao-Yang)", "name_zh": "\u4e1c\u671d\u9633", "num_followed": 0, "num_upvoted": 0, "profile": {"affiliation": "North China Electric Power University Key Lab of Condition Monitoring and Control forPower Plant Equipment,Ministry of Education,Baoding ,China", "org": "North China Electric Power University Key Lab of Condition Monitoring and Control forPower Plant Equipment,Ministry of Education,Baoding ,China"}, "score": 12.315913, "sourcetype": "", "tags": ["Decoupling Integrator Separate", "Multi-Variable", "Coordinated Control System"], "tags_score": [1, 1, 1], "tags_translated_zh": ["\u534f\u8c03\u63a7\u5236\u7cfb\u7edf"]}, {"bind": false, "id": "56254ccf45ce1e5964de6a33", "indices": {"activity": 0, "citations": 0, "diversity": 0, "gindex": 0, "hindex": 0, "newStar": 0, "pubs": 1, "risingStar": 0, "sociability": 2.1972}, "name": "Zhao Dong Yang", "num_followed": 0, "num_upvoted": 0, "score": 12.313169, "sourcetype": "", "tags": [], "tags_translated_zh": []}, {"bind": false, "id": "53f7e94fdabfae9060af7245", "indices": {"activity": 0, "citations": 0, "diversity": 0, "gindex": 0, "hindex": 0, "newStar": 0, "pubs": 0, "risingStar": 0, "sociability": 0}, "name": "Zhao Dong-Yang", "name_zh": "", "num_followed": 0, "num_upvoted": 0, "profile": {"org": ""}, "score": 12.309017, "sourcetype": "", "tags": [], "tags_translated_zh": []}, {"bind": false, "id": "53f464fcdabfaee4dc8483fa", "indices": {"activity": 0.0201, "citations": 0, "diversity": 0, "gindex": 0, "hindex": 0, "newStar": 0, "pubs": 1, "risingStar": 0, "sociability": 1.0986}, "name": "\u4e1c\u671d\u9633(Dong Zhao-Yang)", "name_zh": "\u4e1c\u671d\u9633", "num_followed": 0, "num_upvoted": 0, "profile": {"affiliation": "School of Energy Power and Mechanical Engineering,North China Electric Power University,Baoding ,China", "org": "School of Energy Power and Mechanical Engineering,North China Electric Power University,Baoding ,China"}, "score": 12.309017, "sourcetype": "", "tags": ["Heat Loss Theory", "Heat Efficiency", "Parabolic Trough Collector"], "tags_score": [1, 1, 1], "tags_translated_zh": ["\u70ed\u6548\u7387", "\u69fd\u5f0f\u96c6\u70ed\u5668"]}]}